<?xml version="1.0" encoding="UTF-8" standalone="yes"?>
<addons>
<addon id="plugin.copernicus.sat" name="Copernicus Sat" version="1.1.0" provider-name="jkmh">
  <requires>
    <import addon="xbmc.python" version="3.0.0"/>
	<import addon="script.module.oauthlib" version="3.2.2"/>
	<import addon="script.module.requests_oauthlib" version="1.3.1+matrix.1"/>
	<import addon="script.module.requests" version="2.21.0" />
	<import addon="script.module.beautifulsoup4" version="4.6.3" />
  </requires>
  <extension point="xbmc.python.pluginsource" library="main.py">
     <provides>image</provides>
  </extension>
  <extension point="xbmc.addon.metadata">
    <summary lang="cs_CZ">Stahování družicových snímků</summary>
    <description lang="en_GB"></description>
    <description lang="cs_CZ">Stahujeme družicové snímky Sentinel-2 z programu Copernicus.[CR]Vyzkoušíme generování/stahování čerstvých snímků z družic mise Sentinel-2.[CR][Článek na Živě.cz][CR](https://www.zive.cz/clanky/programujeme-v-pythonu-jak-uplne-zadarmo-stahnout-cerstve-druzicove-snimky-libovolneho-mista-v-cesku/sc-3-a-229892/default.aspx)**</description>
    <license>GPL-3.0-only</license>
    <platform>all</platform>
    <assets>
      <icon>icon.png</icon>
    </assets>
  </extension>
</addon>

<addon id="plugin.image.ws-private-media" name="Webshare Private Media" version="0.7.0" provider-name="Sároš">
    <requires>
        <import addon="xbmc.python" version="3.0.0"/>
        <import addon="script.module.requests"/>
    </requires>
    <extension point="xbmc.python.pluginsource" library="main.py">
        <provides>image audio</provides>
    </extension>
    <extension point="xbmc.service" library="service.py" start="login"/>
    <extension point="xbmc.addon.metadata">
        <assets>
            <icon>icon.jpg</icon>
        </assets>
    </extension>
</addon>

﻿<addon id="plugin.video.antik" name="Antik TV" provider-name="waladir" version="1.0.6">
  <requires>
    <import addon="xbmc.python" version="3.0.0"/>
    <import addon="script.module.requests" version="2.18.4"/>
    <import addon="inputstream.adaptive" version="19.0.0"/>
    <import addon="script.module.inputstreamhelper" version="0.4.2"/>
  </requires>
  <extension library="main.py" point="xbmc.python.pluginsource">
    <provides>video</provides>
  </extension>
  <extension library="service.py" point="xbmc.service"/>
  <extension point="xbmc.addon.metadata">
    <summary lang="en_GB">Antik TV</summary>
    <summary lang="sk_SK">Antik TV</summary>
    <summary lang="cs_CZ">Antik TV</summary>
    <description lang="en_GB">
Doplněk pro Antik TV (CZ i SK)

Další informace a podporu najdete na fóru www.xbmc-kodi.cz (https://www.xbmc-kodi.cz/prispevek-antik-tv--13396)
    </description>
    <description lang="sk_SK">
Doplněk pro Antik TV (CZ i SK)

Další informace a podporu najdete na fóru www.xbmc-kodi.cz (https://www.xbmc-kodi.cz/prispevek-antik-tv--13396)
    </description>
    <description lang="cs_CZ">
Doplněk pro Antik TV (CZ i SK)

Další informace a podporu najdete na fóru www.xbmc-kodi.cz (https://www.xbmc-kodi.cz/prispevek-antik-tv--13396)
    </description>
    <platform>all</platform>
    <source>https://github.com/waladir/plugin.video.antik</source>
    <news>
v1.0.6 (27.5.2025)
- ošetření problémových znaků v EPG

v1.0.5 (22.4.2025)
- oprava přehrávání archivu

v1.0.4 (15.4.2025)
- oprava přehrávání archivu (posun začátku)

v1.0.3 (21.2.2025)
- ošetření chybějících žánrů v datech

v1.0.2 (21.2.2025)
- přidání žánrů
- filtrování kanálů pro archiv/catchup
- úprava linku na fórum
    </news>
    <assets>
        <icon>icon.jpg</icon>
    </assets>
  </extension>
</addon>

<addon id="plugin.video.fastshare" version="2.0.0" name="FASTSHARE" provider-name="info@fastshare.cz, revize jkmh">
  <language></language>
<requires>
  <import addon="xbmc.python" version="3.0.0"/>
  <!--<import addon="plugin.program.autocompletion" version="2020.0.0"/>
  <import addon="script.module.autocompletion" version="2020.0.0"/>-->
</requires>
<extension point="xbmc.python.pluginsource" library="main.py">
  <provides>video</provides>
</extension>
<extension point="xbmc.addon.metadata">
  <summary lang="en_GB">FASTSHARE EN</summary>
  <summary lang="cs_CZ">FASTSHARE CZ</summary>
  <summary lang="pl_PL">FASTSHARE PL</summary>
  <summary lang="sk_SK">FASTSHARE SK</summary>
  <platform>all</platform>
  <description lang="en_GB">Fastshare audio/video plugin for KODI.</description>
  <disclaimer lang="en_GB">Free to use</disclaimer>
  <description lang="cs_CZ">Fastshare audio/video rozšíření pro KODI.</description>
  <disclaimer lang="cs_CZ">Zdarma</disclaimer>
  <description lang="pl_PL">PL Fastshare rozszerzenie audio / wideo dla KODI.</description>
  <disclaimer lang="pl_PL">PL za darmo</disclaimer>
  <description lang="sk_SK">SK Fastshare audio/video rozšírenie pre KODI.</description>
  <disclaimer lang="sk_SK">SK Zdarma</disclaimer>
  <assets>
    <icon>icon.png</icon>
  </assets>
  <news>Verze 1.0.8 - Python 3 compatible, SK language added</news>
</extension>
</addon>

<addon id="plugin.video.filmfinder"
       name="Film Finder"
       version="1.0.0"
       provider-name="TvojeJmeno">
    <requires>
        <import addon="script.module.requests" version="2.18.4"/>
        <import addon="script.module.beautifulsoup4" version="4.5.0"/>
    </requires>
    <extension point="xbmc.python.pluginsource" library="main.py">
        <provides>video</provides>
    </extension>
    <extension point="xbmc.addon.metadata">
        <summary lang="en">Film Finder</summary>
        <description lang="cs">Doplnit</description>
        <disclaimer lang="cz">Doplnit.</disclaimer>
        <platform>all</platform>
        <forum>https://www.xbmc-kodi.cz/prispevek-sktonline</forum>
        <source>https://github.com/cache-sk/SkTonline</source>
        <assets>
            <icon>icon.png</icon>
        </assets>
    </extension>
</addon>

<addon id="plugin.video.hellspy" name="Hellspy.cz" version="1.1.2" provider-name="jkmh, VincoNafta">
	<requires>
	  <import addon="xbmc.python" version="3.0.1"/>
	  <import addon="script.module.requests"/>
	</requires>
	<extension point="xbmc.python.pluginsource" library="default.py">
	  <provides>video</provides>
	</extension>
    <extension point="xbmc.addon.metadata">
        <summary lang="cs">Vyhledávání videí na serveru Hellspy.cz</summary>
        <description lang="cs">Hledej a přehrávej videa z Hellspy.cz Není nutný účet.[CR][CR]Tímto díky @JanoHD za nápad.</description>
        <platform>all</platform>
    	<assets>
			<icon>icon.png</icon>
		</assets>
	</extension>
</addon>

<addon id="plugin.video.idnes.tv" name="iDnes TV" version="1.3.2" provider-name="jkmh">
	<requires>
		<import addon="xbmc.python" version="3.0.0"/>
		<import addon="xbmc.addon" version="14.0.0"/>
		<import addon="script.module.requests"/>
		<import addon="script.module.beautifulsoup4"/>
		<import addon="script.module.routing"/>
		<import addon="script.module.urllib3"/>
		<import addon="script.module.requests" version="2.1.0"/>
		<import addon="script.module.dateutil" version="2.8.1"/>
	</requires>
	<extension library="default.py" point="xbmc.python.pluginsource">
		<provides>video</provides>
	</extension>
	<extension point="xbmc.addon.metadata">
		<summary lang="cs_CZ">iDnes.cz</summary>
		<description lang="cs_CZ">Doplněk umožňuje sledování pořadů z webu tv.idnes.cz a kino.idnes.cz</description>
		<platform>all</platform>
		<assets>
			<icon>icon.png</icon>
		</assets>
	</extension>
</addon>

<addon id="plugin.video.nahnoji.cz"
version="1.0.1"
name="Nahnoji.cz"
provider-name="VincoNafta">
<requires>
  <import addon="xbmc.python" version="3.0.1"/>
  <import addon="script.module.beautifulsoup4" version="4.6.2"/>
  <import addon="script.module.requests"/>
</requires>
<extension point="xbmc.python.pluginsource" library="main.py">
  <provides>video</provides>
</extension>
<extension point="xbmc.addon.metadata">
  <summary>Nahnoji Vyhladavač</summary>
  <description>Vyladavač videii zo servera nahnoji.cz.</description>
  <disclaimer>Nie som zodpovedný za obsah doplnku</disclaimer>
  <license>GPL-3.0-only	</license>
  <assets>
    <icon>resources/images/icon.png</icon>
    <fanart>resources/images/fanart.jpg</fanart>
    <screenshot>resources/images/screenshot-1.jpg</screenshot>
    <screenshot>resources/images/screenshot-2.jpg</screenshot>
  </assets>
</extension>
</addon>

<addon id="plugin.video.sktonline" version="1.1.2" name="SkTonline" provider-name="cache-sk">
    <requires>
        <import addon="script.module.requests" version="2.18.4"/>
        <import addon="script.module.beautifulsoup4" version="4.5.0"/>
    </requires>
    <extension point="xbmc.python.pluginsource" library="main.py">
        <provides>video</provides>
    </extension>
    <extension point="xbmc.addon.metadata">
        <summary lang="en">SkTonline</summary>
        <description lang="en">Simulation of online.sktorrent.eu browser</description>
        <description lang="sk">Simulácia prehliadača stránky online.sktorrent.eu</description>
        <description lang="cs">Simulace prohlížeče stránky online.sktorrent.eu</description>
        <disclaimer lang="en">The plugin does not provide any content, it is only a simulation of the browser of a publicly available web site. I am not responsible for the content provided by this site.</disclaimer>
        <disclaimer lang="sk">Plugin neposkytuje žiaden obsah, je to len simulácia prehliadača verejne dostupnej web stránky. Nie som zodpovedný za obsah, ktorý táto stránka poskytuje.</disclaimer>
        <disclaimer lang="cz">Plugin neposkytuje žádný obsah, je to jen simulace prohlížeče veřejně dostupné web stránky. Nejsem zodpovědný za obsah, který tato stránka poskytuje.</disclaimer>
        <platform>all</platform>
        <forum>https://www.xbmc-kodi.cz/prispevek-sktonline</forum>
        <source>https://github.com/cache-sk/SkTonline</source>
        <assets>
            <icon>icon.png</icon>
        </assets>
        <news>
[B]1.1.2[/B]
- prihlasenie vyzaduje recaptchu, takze je znefunkcnene
[B]1.1.1[/B]
- prototyp prihlasenia pre CZ
[B]1.1.0[/B]
- upravenie vyberu streamu cez kontextove menu a nie submenu, pridanie naposledy pozeranych, pridanie historie vyhladavania
[B]1.0.5[/B]
- i am an idiot fix
[B]1.0.4[/B]
- matrix fix
[B]1.0.3[/B]
- kompatibilita s Kodi 19 Matrix Alpha
[B]1.0.2[/B]
- zviditelnenie v Kodi 19 Matrix Alpha
[B]1.0.1[/B]
- disclaimer
[B]1.0.0[/B]
- first release
        </news>
    </extension>
</addon>

<addon id="plugin.video.stream-cinema-webshare" name="Stream Cinema Webshare" version="2.1.1" provider-name="jkmh">
	<requires>
		<import addon="xbmc.python" version="3.0.0"/>
        <import addon="script.module.requests" version="2.18.4"/>
        <import addon="script.module.unidecode" version="0.4.16"/>
    </requires>
    <extension point="xbmc.python.pluginsource" library="main.py">
        <provides>video</provides>
    </extension>
	<extension point="xbmc.addon.metadata">
		<platform>all</platform>
		<summary lang="en_GB">Stream Cinema Webshare - web storage content player</summary>
        <summary lang="sk_SK">Stream Cinema webshare - prehrávač obsahu webového úložiska</summary>
        <summary lang="cs_CZ">Stream Cinema Webshare - přehrávač obsahu webového úložiště</summary>
		<description lang="cs_CZ">Stream Cinema Webshare - přehrávač obsahu webového úložiště</description>
		<license>GNU General Public License, v2</license>
		<language></language>
		<assets>
			<icon>resources/skins/images/icon.png</icon>
			<fanart>resources/skins/images/fanart.jpg</fanart>
		</assets>
	</extension>
</addon>

<addon id="plugin.video.webshare" name="Webshare video" version="1.1.0" provider-name="jkmh">
    <requires>
        <import addon="xbmc.python" version="3.0.0"/>
		<import addon="script.module.requests" version="2.21.0" />
    </requires>
    <extension point="xbmc.python.pluginsource" library="default.py">
        <provides>video</provides>
    </extension>
    <extension point="xbmc.addon.metadata">
        <summary lang="cs">Vyhledávání videí na serveru Webshare</summary>
        <description lang="cs">Hledej a přehrávej videa z Webshare.cz jinak</description>
        <platform>all</platform>
    	<assets>
			<icon>icon.png</icon>
		</assets>
	</extension>
</addon>

<addon id="plugin.video.yawsp" name="YAWsP" version="0.2.0" provider-name="cache-sk">
    <requires>
        <!--import addon="xbmc.python" version="2.19.0"/-->
        <import addon="script.module.requests" version="2.18.4"/>
        <import addon="script.module.unidecode" version="0.4.16"/>
    </requires>
    <extension point="xbmc.python.pluginsource" library="main.py">
        <provides>video</provides>
    </extension>
    <extension point="xbmc.addon.metadata">
        <summary>Yet Another Webshare Plugin</summary>
        <disclaimer lang="en_GB">The plugin does not provide any content, it is only a simulation of the browser of a publicly available web site. I am not responsible for the content provided by this site.</disclaimer>
        <disclaimer lang="sk_SK">Plugin neposkytuje žiaden obsah, je to len simulácia prehliadača verejne dostupnej web stránky. Nie som zodpovedný za obsah, ktorý táto stránka poskytuje.</disclaimer>
        <disclaimer lang="cs_CZ">Plugin neposkytuje žádný obsah, je to jen simulace prohlížeče veřejně dostupné web stránky. Nejsem zodpovědný za obsah, který tato stránka poskytuje.</disclaimer>
        <platform>all</platform>
        <license>AGPL 3.0</license>
        <forum>https://www.xbmc-kodi.cz/prispevek-yet-another-webshare-plugin</forum>
        <source>https://github.com/cache-sk/plugin.video.yawsp</source>
        <assets>
            <icon>resources/icon.png</icon>
        </assets>
        <news>
[B]0.2.0[/B]
- nexus compatibility
[B]0.1.9[/B]
- matrix compatibility pt3
[B]0.1.8[/B]
- matrix compatibility pt2
[B]0.1.7[/B]
- matrix compatibility pt1
[B]0.1.6[/B]
- experimenty s uuid/headermi aby neukladalo historiu viac krat - nepomohlo..
- uuid je generovane
[B]0.1.5[/B]
- fixed stahovanie, aby slo aj na sambu
[B]0.1.4[/B]
- experimental
[B]0.1.3[/B]
- experimental
[B]0.1.2[/B]
- pridane stahovanie
[B]0.1.1[/B]
- pridane v menu hladania aj vsetky najnovsie a najvacsie (pozor, zobrazuje to aj adult obsah)
[B]0.1.0[/B]
- prvy verejny release
- TODO stahovanie
- TODO hladanie pomocou TMDB
        </news>
    </extension>
</addon>

<addon id="plugin.ws.recorder" name="Webshsre Recorder" version="1.0.0" provider-name="jkmh">
    <requires>
        <import addon="xbmc.python" version="3.0.0"/>
		<import addon="script.module.requests" version="2.21.0" />
    </requires>
    <extension point="xbmc.python.script" library="default.py">
        <provides>video</provides>
    </extension>
	  <extension point="xbmc.addon.metadata">
    <summary lang="cs_CZ">Stahovač streamů</summary>
    <description lang="en_GB"></description>
    <description lang="cs_CZ">Stahovač streamů z webshare</description>
    <license>GPL-3.0-only</license>
    <platform>all</platform>
    <assets>
      <icon>icon2.png</icon>
    </assets>
  </extension>
</addon>

<addon id="repo.kodi.karneval.omega"
		name="Kodi Karneval Omega"
		version="1.0.1"
		provider-name="Team Kodi, jkmh">
  <requires>
    <import addon="xbmc.addon" version="12.0.0"/>
  </requires>
	<extension point="xbmc.addon.repository">
		<!-- Do not forget to bump add-on version when changing paths to force a repo refresh -->
		<dir>
			<info>https://mirror.karneval.cz/pub/xbmc/addons/omega//addons.xml.gz</info>
			<checksum>https://mirror.karneval.cz/pub/xbmc/addons/omega/addons.xml</checksum>
			<datadir>https://mirror.karneval.cz/pub/xbmc/addons/omega/</datadir>
		</dir>
	</extension>
	<extension point="xbmc.addon.metadata">
		<platform>all</platform>
		<assets>
			<icon>icon.png</icon>
		</assets>
		<summary lang="af_ZA">Installeer Byvoegsels vanaf Kodi.tv</summary>
		<summary lang="am_ET">ከ Kodi.tv ተጨማ-ሪዎች መግጠሚያ</summary>
		<summary lang="ar_SA">ثبت إضافات من موقع Kodi.tv الرسمي</summary>
		<summary lang="ast_ES">Instalación de complementos dende Kodi.tv</summary>
		<summary lang="be_BY">Усталяваць дапаўненне з Kodi.tv</summary>
		<summary lang="bg_BG">Инсталира добавки от Kodi.tv</summary>
		<summary lang="ca_ES">Instal·la complements des de Kodi.tv</summary>
		<summary lang="cs_CZ">Instalovat doplňky z Kodi.tv</summary>
		<summary lang="cy_GB">Gosod Ychwanegion o Kodi.tv</summary>
		<summary lang="da_DK">Installer add-ons fra Kodi.tv</summary>
		<summary lang="de_DE">Addons von Kodi.tv installieren</summary>
		<summary lang="el_GR">Εγκατάσταση Προσθέτων από το Kodi.tv</summary>
		<summary lang="en_AU">Install Add-ons from Kodi.tv</summary>
		<summary lang="en_GB">Install Add-ons from Kodi.tv</summary>
		<summary lang="en_NZ">Install Add-ons from Kodi.tv</summary>
		<summary lang="en_US">Install Add-ons from Kodi.tv</summary>
		<summary lang="es_AR">Instalar Add-ons de Kodi.tv</summary>
		<summary lang="es_ES">Instalar Add-ons de Kodi.tv</summary>
		<summary lang="es_MX">Instalar complementos de Kodi.tv</summary>
		<summary lang="et_EE">Paigalda lisasid Kodi.tv lehelt</summary>
		<summary lang="eu_ES">Instalatu Kodi.tv-eko gehigarriak</summary>
		<summary lang="fa_IR">نصف افزونه‌ها از Kodi.tv</summary>
		<summary lang="fi_FI">Asenna lisäosia Kodi-tv-palvelusta</summary>
		<summary lang="fr_CA">Installer des addiciels depuis Kodi.tv</summary>
		<summary lang="fr_FR">Installer des modules complémentaires à partir de Kodi.tv</summary>
		<summary lang="gl_ES">Instalar complementos dende Kodi.tv</summary>
		<summary lang="he_IL">התקנת הרחבות מ־Kodi.tv</summary>
		<summary lang="hr_HR">Instaliraj dodatke s Kodi.tv</summary>
		<summary lang="hu_HU">Kiegészítők letöltése az Kodi.tv-ról</summary>
		<summary lang="id_ID">Pasang Pengaya dari Kodi.tv</summary>
		<summary lang="is_IS">Setja inn viðbætur frá Kodi.tv</summary>
		<summary lang="it_IT">Installa add-on da Kodi.tv</summary>
		<summary lang="ja_JP">Kodi.tv からアドオンをインストール</summary>
		<summary lang="ko_KR">Kodi.tv의 애드온 설치</summary>
		<summary lang="lt_LT">Įdiegti priedus iš Kodi.tv</summary>
		<summary lang="lv_LV">Instalēt pielikumus no Kodi.tv</summary>
		<summary lang="mk_MK">Инсталирај Додатоци од Kodi.tv</summary>
		<summary lang="ms_MY">Pasang tambahan daripada Kodi.tv</summary>
		<summary lang="mt_MT">Installa Add-ons minn Kodi.tv</summary>
		<summary lang="my_MM">Kodi.tv မှ Add-on များကိုသွင်းမည်</summary>
		<summary lang="nb_NO">Installer utvidelser fra Kodi.tv</summary>
		<summary lang="nl_NL">Add-ons van Kodi.tv installeren</summary>
		<summary lang="pl_PL">Instaluj dodatki z Kodi.tv</summary>
		<summary lang="pt_BR">Instale Add-ons do Kodi.tv</summary>
		<summary lang="pt_PT">Instalar Add-ons a partir de Kodi.tv</summary>
		<summary lang="ro_RO">Instalați suplimente de la Kodi.tv</summary>
		<summary lang="ru_RU">Установка дополнений с сайта Kodi.tv</summary>
		<summary lang="sk_SK">Inštalovať doplnky z Kodi.tv</summary>
		<summary lang="sl_SI">Namestite dodatke s Kodi.tv</summary>
		<summary lang="sr_RS">Инсталирај додатне програме са Kodi.tv</summary>
		<summary lang="sr_RS@latin">Instaliraj dodatne programe sa Kodi.tv</summary>
		<summary lang="sv_SE">Installera tillägg från Kodi.tv</summary>
		<summary lang="szl">Insztaluj przidŏwki ze Kodi.tv</summary>
		<summary lang="tg_TJ">Насб кардани барномаҳои иловагӣ аз Kodi.tv</summary>
		<summary lang="th_TH">ติดตั้งส่วนเสริมจาก Kodi.tv</summary>
		<summary lang="tr_TR">Kodi.tv sitesinden eklentileri yükleyin</summary>
		<summary lang="uk_UA">Встановити додатки з Kodi.tv</summary>
		<summary lang="vi_VN">Cài đặt Add-on từ Kodi.tv</summary>
		<summary lang="zh_CN">从 Kodi.tv 安装插件</summary>
		<summary lang="zh_TW">從 Kodi.tv 安裝附加元件</summary>
		<description lang="af_ZA">Laai af en installeer byvoegsels vanaf die amptelike Kodi.tv byvoegsel kodebank.[CR] Deur die amptelike Kodebank te gebruik trek jy voordeel van ons uitgebreide lêer spieël diens wat jou help vinniger aflaai vanaf &apos;n gebied naby aan jou.[CR] Alle byvoegsels in hierdie kodebank het basiese toetsing ondergaan, as jy &apos;n gebreekte of nie werkende byvoegsel vind rapporteer dit asseblief aan die Kodi Span sodat ons die nodige stappe kan neem.</description>
		<description lang="ar_SA">حمل و ثبت الإضافات من مستودع الإضافات لموقع Kodi.tv الرسمي.[CR] باستخدامك المستودع الرسمي ستكون قادر على الاستفادة مما نقدمه من خدمة حصرية لتوفير خوادم بديله لتحميل الملفات توفر لك سرعة تحميل أعلى من منطقه قريبة منك.[CR] جميع الإضافات في هذا المستودع خضعت لاختبارات مبدئية, إذا صادفتك إضافة معطوبة أو لا تعمل برجاء الإبلاغ عنها لفريق Kodi لنتمكن من اتخاذ الإجراء اللازم.</description>
		<description lang="ast_ES">Baxa ya instala complementos dende&apos;l depósitu de complementos de Kodi.tv.[CR]  Pente l&apos;usu del depósitu oficial vas poder aprovechar les ventayes del nuesu espeyu de ficheros p&apos;ayudate a consiguir descargues más rápides dende una rexón lo más cercana a ti.[CR]  Tolos complementos d&apos;esti depósitu sométense a pruebes básiques, polo que si atopes dalgún complementu estropiáu o que nun funciona díy-lo al equipu de Kodi pa que puedan tomar les aiciones afayadices.</description>
		<description lang="be_BY">Спампаваць і ўсталяваць дапаўненне з афіцыйнага рэпазіторыя Kodi.tv . [CR] Пры выкарыстанні афіцыйнага рэпазіторыя вы зможаце выкарыстаць нашу службу люстэрак, каб у вас была больш вышэйшая хуткасць спампоўвання з рэгіёна, бліжэйшага да вас. [CR] Усе дапаўненні ў гэтым рэпазіторыя былі пратэставаныя. Калі вы выявілі пашкоджанае дапаўненне, ці дапаўненне, якое не працуе, калі ласка, паведаміце пра гэта камандзе Kodi, каб мы маглі гэта выправіць.</description>
		<description lang="bg_BG">Сваля и инсталира добавки от официалното хранилище за добавки на Kodi.tv. Ползвайки добавката ще се възползвате от системата ни от огледални сървъри - за да сваляте с висока скорост, от сървър близък до Вас. Добавките от хранилището са минали няколко теста, но ако се натъкнете на неработеща или проблемна добавка, моля уведомете екипа на Kodi, за да бъдат предприети необходимите действия.</description>
		<description lang="ca_ES">Baixeu i instal·leu els complements des del dipòsit oficial de Kodi.tv.[CR] Mitjançant el dipòsit oficial, podreu aprofitar els avantatges del nostre servei de rèplica de fitxers per ajudar-vos a tenir unes baixades més ràpides des d&apos;una regió que estigui a prop vostre.[CR] Tots els complements d&apos;aquest dipòsit han passat per proves bàsiques, així que si trobeu algun complement que no funcioni correctament, si us plau, digueu-ho a l&apos;equip de Kodi perquè puguin dur a terme les accions pertinents.</description>
		<description lang="cs_CZ">Stáhnout a nainstalovat doplňky z oficiálního repozitáře doplňků Kodi.tv.[CR] Použitím oficiálního repozitáře budete moci využít naši rozsáhlou službu zrcadel souborů, která vám pomůže rychleji stahovat z oblasti blízko vás.[CR] Všechny doplňky v tomto repozitáři prošly základním testováním. Pokud najdete rozbitý nebo nefunkční doplněk, oznamte to týmu Kodi, abychom mohli přijmout veškerá nezbytná opatření.</description>
		<description lang="cy_GB">Llwytho i lawr a gosod ychwanegion o storfa ychwanegion Swyddogol Kodi.tv.{CR}Drwy ddefnyddio&apos;r Storfa swyddogol bydd modd i chi gymryd mantais o&apos;n gwasanaeth drychau ffeiliau i&apos;ch cynorthwyoi lwytho i lawr yn gyflym o ardal yn agos i chi.[CR] Mae pob ychwnaegyn yn y storfa hwn wedi eu profi&apos;n fras, os ydych yn canfod ychwanegyn sydd wedi torri  neu ddim yn gweithio yna hysbyswch Team Kodi fel bod modd i ni weithredu.</description>
		<description lang="da_DK">Hent og installer add-ons fra det officielle Kodi.tv add-on fjernlager.[CR]Ved at bruge det officielle fjernlager drager du fordel af vores omfattende spejltjeneste, som gør at du kan hente hurtigere fra et sted nær dig.[CR]Alle add-ons i dette fjernlager har gennemgået grundlæggende tests. Hvis du finder en defekt add-on, så rapporter venligst dette til Team Kodi, så vi kan tage hånd i hanke med eventuelle problemer.</description>
		<description lang="de_DE">Addons aus dem offiziellen Kodi.tv-Addon-Repository herunterladen und installieren[CR]. Ein Vorteil davon ist, dass dann ein Filespiegelungsservice für schnellere Downloads aus einer nahegelegenen Region verwendet wird.[CR]. Alle Addons dieses Repositories wurden grundllegend getestet. Falls ein Addon nicht richtig funktioniert, bitte an Team Kodi wenden.</description>
		<description lang="el_GR">Πραγματοποιήστε λήψη και εγκατάσταση προσθέτων από το επίσημο αποθετήριο του Kodi.tv.[CR]  Χρησιμοποιώντας το Επίσημο Αποθετήριο μπορείτε να εκμεταλλευτείτε τους εκτεταμένους διακομιστές αρχείων μας για ταχύτερες λήψεις από μία κοντινή σας περιοχή.[CR]  Όλα τα πρόσθετα σε αυτό το αποθετήριο έχουν περάσει τις στοιχειώδεις δοκιμές, αν βρείτε ένα κατεστραμμένο ή ανενεργό πρόσθετο παρακαλούμε να το αναφέρετε στην Ομάδα Kodi ούτως ώστε να πραγματοποιηθούν οι απαραίτητες ενέργειες.</description>
		<description lang="en_AU">Download and install add-ons from the Official Kodi.tv add-on repository.[CR]  By using the official Repository you will be able to take advantage of our extensive file mirror service to help get you faster downloads from a region close to you.[CR]  All add-ons on this repository have undergone basic testing, if you find a broken or not working add-on please report it to Team Kodi so we can take any action needed.</description>
		<description lang="en_GB">Download and install add-ons from the Official Kodi.tv add-on repository.[CR]  By using the official Repository you will be able to take advantage of our extensive file mirror service to help get you faster downloads from a region close to you.[CR]  All add-ons on this repository have under gone basic testing, if you find a broken or not working add-on please report it to Team Kodi so we can take any action needed.</description>
		<description lang="en_NZ">Download and install add-ons from the Official Kodi.tv add-on repository.[CR]  By using the official Repository you will be able to take advantage of our extensive file mirror service to help get you faster downloads from a region close to you.[CR]  All add-ons on this repository have under gone basic testing, if you find a broken or not working add-on please report it to Team Kodi so we can take any action needed.</description>
		<description lang="en_US">Download and install add-ons from the Official Kodi.tv add-on repository.[CR]  By using the official Repository you will be able to take advantage of our extensive file mirror service to help get you faster downloads from a region close to you.[CR]  All add-ons on this repository have under gone basic testing, if you find a broken or not working add-on please report it to Team Kodi so we can take any action needed.</description>
		<description lang="es_AR">Descarga e instala el complemento desde el repositorio oficial de Kodi.tv.[CR] Usando el repositorio oficial tendrá las ventajas de nuestro servicio de réplicas para ayudarle a conseguir unas descargas más rápidas de un sitio cercano a su región.[CR] Todos los complementos en este repositorio han pasado por un periodo de pruebas básico, pero si encuentra algún complemento que no funciona, por favor infórmelo al equipo de Kodi para que podamos tomar las acciones necesarias.</description>
		<description lang="es_ES">Descarga e instala Add-ons desde el repositorio de Add-ons Oficial de Kodi.tv[CR]  Usar el repositorio oficial habilita la ventaja de nuestro servicio de archivos espejo que ayudan a descargar más rápido desde la región mas cercana.[CR]  Todos los Add-ons de este repositorio se han probado básicamente, pero si encuentra un Add-on roto o que no funcione correctamente, por favor, reporte el problema al Equipo Kodi para que pueda tomar la acción necesaria.</description>
		<description lang="es_MX">Descarga e instala complementos del repositorio oficial de Kodi.tv.[CR] Al usar el repositorio oficial, tienes la ventaja de los servicios de réplicas para tener descargas más rápidas.[CR] Todos los complementos en este repositorio se han probado de manera básica, si encuentras alguno roto o que no funciona, por favor repórtalo al equipo de Kodi para poder tomar las medidas necesarias.</description>
		<description lang="et_EE">Lae alla ja installi lisasid ametlikust Kodi.tv hoidlast.[CR]  Ametliku hoidla kasutamise eeliseks on võimalus kasutada meie ulatuslikku failide peegelteenust laadides faile sulle kõige lähemast serverist.[CR]  Kõik lisad selles hoidlas on läbinud elementaarse testimise. Siiski, kui sa leiad vigase või mittetöötava lisa, siis palun teavita sellest Kodi meeskonda, et me saaksime vajaliku abi osutada.</description>
		<description lang="eu_ES">Deskargatu eta instalatu gehigarriak Kodi.tv biltegi ofizialetik.[CR]  [CR]Biltegi ofiziala erabiliz zugandik gertu dagoen gune batetik deskargatu[CR]ditzakezu gure fitxategi-ispilu zerbitzu zabalaren abantailaz aprobetxatuaz.[CR]  [CR]Biltegi honetako gehigarri guztiek oinarrizko probak gainditu dituzte baina hondaturiko edo funtzionatzen ez duen gehigarri baten bat aurkituz gero jakinarazi Kodi taldeari beharrezko ekintzak burutu ditzagun.</description>
		<description lang="fa_IR">افزودنی ها را از منبع رسمی افزونه ها در Kodi.tv دانلود و نصب کنید. [CR] با استفاده از منبع رسمی شما قادر خواهید بود از خدمات گسترده سرویس دانلود جایگزین ما بهره ببرید که امکان دانلود از مناطق نزدیکتر را در اختیار شما قرار می دهد. [CR] همه افزونه های این منبع آزمایش های اولیه را پشت سر گذاشته اند. در صورت یافتن افزونه معیوب یا غیر قابل استفاده لطفا آن را به تیم کودی گزارش کنید تا اقدامات لازم را انجام دهیم.</description>
		<description lang="fi_FI">Lataa ja asenna lisäosia virallisesta Kodi.tv-jakeluvarastosta.[CR] Virallista varastoa käyttämällä hyödyt laajasta tiedostopeilipalvelustamme, jonka avulla saat nopeammat lataukset sinua lähimmästä lähteestä.[CR] Kaikille varaston lisäosille on tehty perustestaus, mutta jos löydät viallisen tai toimimattoman lisäosan, ilmoita siitä Team Kodille, jotta voimme tarvittaessa ryhtyä toimiin.</description>
		<description lang="fr_CA">Télécharger et installer des addiciels depuis le dépôt officiel de Kodi.tv.[CR] En utilisant le dépôt officiel vous pourrez bénéficier de notre service étendu de miroirs de fichiers favorisant des téléchargements plus rapides depuis une région proche de vous.[CR] Tous les addiciels de ce dépôt ont subi des tests de base. Si vous trouvez un addiciel non fonctionnel ou brisé, veuillez le rapporter à l’équipe Kodi afin que nous puissions agir.</description>
		<description lang="fr_FR">Télécharger et installer des modules complémentaires à partir du magasin de modules complémentaires officiel Kodi.tv.[CR] En utilisant le magasin officiel, vous pourrez profiter de notre service de miroir de fichiers étendu pour vous aider à obtenir des téléchargements plus rapides depuis une région proche de chez vous. .[CR] Tous les modules complémentaires de ce magasin ont subi des tests de base. Si vous trouvez un module complémentaire cassé ou qui ne fonctionne pas, veuillez le signaler à l&apos;équipe Kodi afin que nous puissions prendre les mesures nécessaires.</description>
		<description lang="gl_ES">Descargar e instalar complementos dende o repositorio oficial de Kodi.tv.[CR] Empregando o repositorio oficial, poderás gozar das vantaxes do seu extenso servizo de replicación de ficheiros que che permite unhas descargas máis rápidas dende unha rexión preto á túa.[CR] Tódolos complementos deste repositorio pasaron por comprobacións básicas. Se atopas algún complemento roto ou non funcional, por favor informa ao equipo de Kodi para que poidan actuar en consecuencia.</description>
		<description lang="he_IL">הורדה והתקנת הרחבות ממאגר הרחבות Kodi.tv הרשמי.[CR] שימוש במאגר הרשמי מאפשר לנצל את שירות שיקוף הקבצים של Kodi.tv העוזר להוריד מהר יותר מהשרת הקרוב ביותר.[CR] כל ההרחבות במאגר זה עברו בדיקה בסיסית. יש לדווח לצוות הפיתוח של Kodi על כל הרחבה שנמצאה כלא תקינה או שלא עובדת ע&quot;מ שתתבצע הפעולה המתאימה.</description>
		<description lang="hr_HR">Preuzmite i instalirajte dodatke sa službenog Kodi.tv repozitorija dodataka.[CR] Korištenjem službenog repozitorija bit ćete u mogućnosti iskoristiti prednosti usluge našeg brzog zrcalnog poslužitelja datoteka, kako bi mogli brže preuzimati iz regije koje je bliže vašoj lokaciji.[CR] Svi dodaci na ovom repozitoriju prošli su osnovno testiranje, u slučaju da primijetite neispravan dodatak, molimo vas da to prijavite Kodi timu koji će zatim poduzeti potrebne korake.</description>
		<description lang="hu_HU">Kiegészítők letöltése és telepítése a hivatalos Kodi.tv tárolóhelyről.[CR] A hivatalos tárolóhely használatával kihasználhatod szerteágazó tükör-kiszolgáló hálózatunkat, ami segít a gyorsabb letöltésben egy hozzád közelebb eső körzet használatával.[CR]  Minden kiegészítő ezen a tárolóhelyen átment egy alaptesztelésen. Ha mégis hibás vagy nem működő kiegészítőt találsz, kérünk jelezd az Kodi csapatnak, hogy megtegyük a szükséges lépéseket.</description>
		<description lang="id_ID">Unduh dan pasang pengaya dari repositori pengaya resmi Kodi.tv. [CR] Dengan menggunakan repositori resmi anda akan mendapat keuntungan dari miror berkas kami yang luas dimana dapat membantu anda untuk lebih cepat mengunduh dari daerah yang dekat dengan anda. [CR] Semua pengaya pada repository telah melalui uji coba standar, jika anda menemukan pengaya yang rusak atau tidak bekerja tolong laporkan kepada tim Kodi agar kami bisa menindak lanjutinya.</description>
		<description lang="is_IS">Sækja og setja inn viðbætur frá hinu viðurkennda Kodi.tv viðbótasafni.[CR] Með því að nota þetta safn getur þú nýtt þér möguleikann á fullkominni speglunarþjónustu sem hjálpar við að sækja hraðar viðbætur frá landsvæði nálægt þér.[CR] Allar viðbætur í þessu safni hafa gengið undir grunnprófanir, ef þú finnur viðbætur sem eru bilaðar eða virka ekki, endilega láttu Kodi-teymið vita svo við getum gert eitthvað í málinu.</description>
		<description lang="it_IT">Scarica e installa add-on dal repository ufficiale degli add-on di Kodi.tv.[CR] Utilizzando il repository ufficiale sarai in grado di sfruttare il nostro ampio servizio di mirroring dei file per aiutarti a ottenere download più veloci da una regione vicino a te .[CR] Tutti gli add-on su questo repository sono stati sottoposti a test di base: se trovi un add-on non funzionante, segnalalo al Team Kodi in modo che possiamo intraprendere tutte le azioni necessarie.</description>
		<description lang="ja_JP">オフィシャルの Kodi.tv リポジトリからアドオンをダウンロードします。[CR]  オフィシャルリポジトリを使うことで、お住まいのエリアに近いミラーサーバーから高速にアドオンをダウンロードすることが可能です。[CR]  このリポジトリ上のアドオンは全て、簡単な動作テストを受けてはいますが、もしアドオンがおかしかったりうまく動作しなかったりした場合は、Kodi チームに連絡をお願いします。</description>
		<description lang="ko_KR">공식 Kodi.tv 애드온 저장소에서 애드온을 내려받아 설치합니다.[CR] 공식 저장소를 사용하면 넓은 파일 미러 서비스를 활용하여 가까운 지역에서 더 빠르게 내려받을 수 있습니다. .[CR] 이 저장소의 모든 추가 기능은 기본 테스트를 거쳤습니다. 손상되거나 작동하지 않는 애드온을 발견하면 필요한 조치를 취할 수 있도록 Kodi팀에 알려주세요.</description>
		<description lang="lt_LT">Atsisiųskite ir įdiegite priedus iš oficialios Kodi.tv saugyklos.[CR]Naudojantis oficialia saugykla, galėsite pasinaudoti pranašumu mūsų didele failų veidrodinę paslauga.[CR]Taip pat siekiame padėti jums greičiau parsisiųsti priedą iš Jūsų regiono.[CR]Visiems šioje saugykloje saugomiems priedams buvo atliktas testavimas, jei Jūs radote netaisyklingą ir nedarbinį priedą.[CR]Prašome pranešti apie tai Kodi komandai, kad mes galėtume imtis būtinų veiksmų</description>
		<description lang="lv_LV">Lejupielādējiet un instalējiet pielikumus no oficiālā Kodi.tv pielikumu repozitorija[CR] Izmantojot oficiālo repozitoriju, varēsiet izmantot mūsu plašo spoguļu pakalpojumu, lai iegūtu ātrākas lejupielādes no reģiona, kas vistuvāk.[CR] Visi pielikumi šajā repozitorijā ir izgājuši pamata testēšanu, bet, ja atrodat saplīsušu vai nestrādājošu pielikumu, lūdzu, ziņojiet par to Team Kodi, lai varam izpildīt nepieciešamās labošanas darbības.</description>
		<description lang="mk_MK">Превземи и инсталирај Додатоци од официјалниот Kodi.tv склад.[CR] Со користење на официјалниот склад ќе бидете во можност да ги користите предностите на нашата богата датотека со услуги која ви помага да добиете побрзи превземања од регионот блиску до вас.[CR]  Сите Додатоци во овој склад се основно тестирани, ако најдете неисправни или додатоци кои не работат пријавете го тоа на тимот на Kodi така што ќе можеме да превземеме било каква акција што е потребна.</description>
		<description lang="ms_MY">Muat turun dan pasang tambahan PVR melalui repositori rasmi Kodi.tv[CR]  Dengan menggunakan Repositori rasmi anda dapat perkhidmatan cermin fail yang luas supaya dapat memuat turun lebih pantas menerusi kawasan berhampiran anda.[CR]  Semua tambahan di dalam repositori ini telah lulus pengujian asas, jika anda temui tambahan yang rosak atau tidak berfungsi sila laporkannya kepada Team Kodi supaya kami boleh membuat tindakan yang sewajarnya.</description>
		<description lang="mt_MT">Niżżel u nstalla add-ons mir-repożitorju uffiċjali ta Kodi.tv.[CR] Permezz ta&apos; dan ir-ripożitorju uffiċjali tista&apos; tieħu vantaġġ mis-servizz ta&apos; file mirrors estensiv li jgħinek tniżżel l-add-ons iktar malajr minn postijiet li huma ġeografikament qrib tiegħek.[CR] L-Add-ons kollha f&apos;dan ir-repożitorju għaddew minn testijiet bażiċi, f&apos;każ li tinzerta xi add-on miksura jew mhux taħdem jekk jpgħġbok irrportha lil Team Kodi biex inkunu nistgħu nieħdu l-azzjoni li jkun hemm bżonn.</description>
		<description lang="nb_NO">Last ned og installer utvidelser fra den offisielle Kodi.tv-pakkebrønnen.[CR] Når du benytter den offisielle pakkebrønnen kan du dra nytte av vår omfattende arkivtjeneste slik at du får raskere nedlasting fra en tjener nær deg.[CR] Alle tillegg i denne brønnen har gått gjennom grunnleggende testing, men hvis du finner en utvidelse som ikke fungerer, rapporter det til Team Kodi, så vi får sett på det.</description>
		<description lang="nl_NL">Download en installeer add-ons uit de officiële Kodi.tv add-on depot.[CR]Wanneer u de officiële depot gebruikt beschikt u over onze uitgebreide mirrorservice, waardoor u snel kunt downloaden van locaties in uw buurt.[CR] Alle add-ons in dit depot ondergingen standaardtests. Indien u een defecte of niet-werkende add-on vindt, meld dit dan aan Team Kodi zodat zij actie kunnen ondernemen.</description>
		<description lang="pl_PL">Pobieraj i instaluj dodatki z oficjalnego repozytorium dodatków Kodi.tv.[CR]  Korzystając z oficjalnego repozytorium, uzyskujesz dostęp do naszej obszernej usługi kopii lustrzanej plików, aby przyspieszyć pobieranie z regionu blisko Ciebie.[CR]  Wszystkie dodatki w tym repozytorium przeszły podstawowe testy. Jeśli znajdziesz uszkodzony lub niedziałający dodatek, zgłoś to zespołowi Kodi, abyśmy mogli podjąć wszelkie niezbędne działania.</description>
		<description lang="pt_BR">Transfira e instale add-ons a partir do repositório oficial do Kodi.tv.[CR]|Ao utilizar o repositório oficial, você será capaz de tirar proveito do nosso serviço de espelhamento de arquivos, auxiliando em downloads mais rápidos a partir de uma região perto de você.[CR]|Todos os add-ons neste repositório passam por testes básicos, se você encontrar algum quebrado ou que não esteja funcionando, por favor reporte para a equipe do Kodi, para que possamos tomar as ações necessárias.</description>
		<description lang="pt_PT">Transferir e instalar add-ons a partir do repositório de add-ons oficiais de Kodi.tv.[CR]Ao utilizar o Repositório oficial, irá beneficiar do nosso serviço de servidores de ficheiros para o ajudar a ter transferências mais rápidas da região mais perto de si.[CR]Todos os Add-ons neste repositório foram alvo de testes básicos. Se encontrar um danificado ou que não funciona, por favor, informe Tema Kodi, para que a situação seja resolvida.</description>
		<description lang="ro_RO">Descărcați și instalați suplimente din depozitul de suplimente Kodi.tv oficial.[CR]  Folosind depozitul (repository) oficial puteți beneficia de serviciul nostru de găzduire distribuită pentru a vă ajuta să descărcați mai repede dintr-o regiune mai apropiată de dumneavoastră.[CR]  Toate suplimentele din acest depozit au trecut testele de bază, în caz că găsiți un supliment defect vă rugăm să îl raportați echipei Kodi pentru a lua măsurile necesare.</description>
		<description lang="ru_RU">Загружайте и устанавливайте дополнения из официального репозитория Kodi.tv.[CR]  Используя официальный репозиторий, вы получаете доступ к нашим обширным сервисам, которые позволяют загружать файлы из ближайшего к вам региона.[CR]  Все дополнения в этом репозитории прошли базовое тестирование, если вы обнаружите сломанное или неработающее дополнение, пожалуйста, сообщите об этом в Team Kodi, чтобы мы могли принять необходимые меры.</description>
		<description lang="sk_SK">Stiahnuť a nainštalovať doplnky z oficiálneho repozitára doplnkov Kodi.tv.[CR] Použitím oficiálneho repozitára získavate možnosť využiť rozsiahly systém serverov, ktorý Vám umožní rýchlejšie sťahovanie z vám blízkeho regiónu.[CR] Všetky doplnky v tomto repozitári boli podrobené základnému testovaniu. Ak nájdete poškodené alebo nefunkčné doplnky, oznámte to prosím tímu Kodi aby mohol podľa potreby zakročiť.</description>
		<description lang="sl_SI">Prenos in namestitev dodatkov iz uradnega skladišča Kodi.tv.[CR] Z uporabo uradnega skladišča, boste lahko izkoristili hitrejšo povezavo, ki bo izbrana glede na vašo lokacijo.[CR] Vsi dodatki tega skladišča so bili osnovno stestirani, če pa boste našli pokvarjen ali nedelujoč dodatek, to sporočite ekipi Kodi, da bomo lahko odpravili napake.</description>
		<description lang="sr_RS">Преузмите и инсталирајте додатке из Званичног Kodi.tv спремишта додатака.[CR] Коришћењем званичног Спремишта моћићете да искористите предности нашег сервиса копија фајлова који ће вам помоћи приликом бржег преузимања из региона ближег вашој локацији.[CR] Сви додаци у овом спремишту прошли су основно тестирање, у случају да пронађете неисправан додатак молимо вас да то пријавите Kodi тиму који ће затим предузети неопходне мере.</description>
		<description lang="sr_RS@latin">Preuzmi i instaliraj dodatne programe iz Zvaničnog Kodi.tv spremišta za dodatne programe.[CR] Korišćenjem zvaničnog Spremišta moći ćete da iskoristite prednosti našeg servisa kopija fajlova koji će vam pomoći prilikom bržeg preuzimanja iz regiona bližeg vašoj lokaciji.[CR] Svi dodatni programi u ovom spremištu prošli su osnovno testiranje, u slučaju da pronađete neispravan dodatni program molimo vas da to prijavite Kodi timu koji će zatim preduzeti neophodne mere.</description>
		<description lang="sv_SE">Hämta och installera tillägg från det officiella Kodi.tv tilläggsförrådet.[CR] Genom att använda det officiella förrådet kommer du att få fördelen att kunna använda vår omfattande spegeltjänst som kommer att hjälpa dig till snabbare hämtningar från en plats nära dig.[CR] Alla tillägg i detta förråd har genomgått grundläggande tester. Hittar du ett trasigt eller icke fungerande tillägg, vänligen meddela detta till Team Kodi så att vi kan vidta nödvändiga åtgärder.</description>
		<description lang="szl">Sebiyrej i insztaluj przidŏwki z ôficjalnygo repozytoriōm Kodi.tv.[CR] Przi Używaniu ôficjalnygo repozytoriōm używŏsz serwerōw zdrzadłowych, rozsianych po calistym świecie. Ôbiyrany je tyn, kery je nŏjbliżyj ciebie, co istuje srogõ wartkość skuplowaniŏ.[CR]Wszyjske przidŏwki w tym repozytoriōm sōm testowane, ale mogōm pokŏzać sie popszniōne. Zgłoś wtynczŏs feler, coby ekipa Kodi mogła go sprŏwić.</description>
		<description lang="tg_TJ">Барномаҳои иловагиро аз анбори нармафзори Kodi.tv боргирӣ кунед ва насб намоед.[CR]  Аз истифодаи анбори нармафзори расмии мо ба шумо имконият пайдо мешавад, ки тавонед шароити мусофидро аз хидмати оинаи файлии васеъ ба даст оред ва нармафзори лозимиро аз сервери минтакаи ба шумо наздиктар бо суръати баланд боргирӣ кунед.[CR]  Ҳамаи барномаҳо аз анбори нармафзори мо дар ҳолати санҷишӣ мебошанд, бинобар ин агар ягон барномаи иловагии нуқсондор ё вайроншударо ёбед, лутфан дар бораи он барнома ва нуқсон пайдошуда ба гурӯҳи кории Kodi гузориш диҳед, то ин ки мо тавонем ҳамаи камбудиҳои барномаҳои моро ҳал кунем.</description>
		<description lang="th_TH">ดาวน์โหลดและติดตั้งส่วนเสริม จากแหล่งข้อมูลโปรแกรมของ Kodi.tv อย่างเป็นทางการ.[CR]  โดยการใช้งานแหล่งข้อมูลโปรแกรมอย่างเป็นทางการ คุณสามารถใช้ประโยชน์จากบริการแฟ้มมิเรอร์ที่กว้างขวางของเรา ที่จะช่วยให้การดาวน์โหลดของคุณเร็วขึ้นจากภูมิภาคที่ใกล้ที่สุด.[CR]  ส่วนเสริม ทั้งหมดในแหล่งเก็บข้อมูลนี้ อยู่ภายใต้การทดสอบขั้นพื้นฐานแล้ว ถ้าคุณพบส่วนเสริมที่เสียหายหรือไม่ทำงาน กรุณาแจ้งทีมงาน Kodi เพื่อให้เราสามารถดำเนินการใด ๆ ที่จำเป็น.</description>
		<description lang="tr_TR">Eklentileri resmi Kodi.tv eklenti deposundan indirin ve yükleyin.[CR]Resmi yazılım depomuzu kullanarak size en yakın bölgeden en hızlı biçimde indirme yapmanızı sağlayacak gelişkin dosya aynalama servisini kullanma avantajını elde edeceksiniz.[CR]Bu yazılım deposundaki tüm eklentiler temel testlerden geçerler, şayet hatalı ya da çalışmayan bir eklenti bulursanız lütfen düzeltilmesi için bu durumu Kodi Takımına bildiriniz.</description>
		<description lang="uk_UA">Завантажити і встановити додатки з Офіційного репозиторію додатків Kodi.tv.[CR]  Використовуючи Офіційний Репозиторій ви отримаєте перевагу надану нашими дзеркальними серверами, які забезпечать вам швидке завантаження із найближчого до вас регіону.[CR]  Всі додатки в цьому Репозиторії пройшли лише базове тестування. Якщо ви знайшли зламаний або непрацюючий додаток, будь-ласка повідомте про це Команду Kodi щоб ми могли вжити потрібних заходів.</description>
		<description lang="vi_VN">Tải về và cài đặt tiện ích từ kho tiện ích chính thức của Kodi.[CR]  Khi sử dụng kho lưu trữ này bạn sẽ hưởng lợi từ dịch vụ nguồn của chúng tôi, giúp bạn có thể tải về nhanh hơn từ một khu vực gần bạn.[CR]  Tất cả tiện ích trên kho lưu trữ này đã được thông qua bài kiểm tra cơ bản, nếu bạn phát hiện ra một tiện ích không hoạt động xin vui lòng báo cáo lại nó cho đội ngũ Kodi để chúng tôi có thể kịp thời xử lý.</description>
		<description lang="zh_CN">从 Kodi.tv 官方插件库下载并安装插件。[CR]通过使用官方插件库，您将能够利用我们遍布各地的文件镜像服务，就近高速下载。[CR]本插件库中的所有插件都已进行基本测试，如果您发现损坏或无法工作的插件，请报告给 Kodi 团队，以便我们及时处理。</description>
		<description lang="zh_TW">從 Kodi.tv 官方的附加元件庫下載並安裝附加元件。[CR] 使用官方的附加元件庫你可以從離你較近的檔案鏡像伺器以較快的速度下載附加元件。[CR] 在這個附加元件庫中的附加元件都經過簡單的測試，如果你發現損壞或無法正常工作的附加元件，請回報給 Kodi 團隊，以讓 Kodi 團隊能做一些必須的處置。</description>
		<disclaimer lang="af_ZA">Die Kodi span het nie al die byvoegsels in hierdie kodebank geskep nie en is nie verantwoordelik vir hulle inhoud nie</disclaimer>
		<disclaimer lang="am_ET">የ Kodi ቡድን እዚህ ማጠራቀሚያ ውስጥ ያሉትን የ ተጨማ-ሪዎች ይዞታ አልፈጠሩም ስለዚህም ምንም አይነት ሀላፊነት አይወስዱም</disclaimer>
		<disclaimer lang="ar_SA">فريق Kodi لم يقم بصنع جميع اﻹضافات فى هذا المستودع وغير مسؤول عن محتواها</disclaimer>
		<disclaimer lang="ast_ES">L&apos;equipu de Kodi nun creó tolos complementos d&apos;esti depósitu nin ye responsable del so conteníu</disclaimer>
		<disclaimer lang="be_BY">Каманда Kodi не распрацоўвае усё дапаўненні з гэтага рэпазіторыя і не нясе адказнасці за іх змесціва</disclaimer>
		<disclaimer lang="bg_BG">Екипът на Kodi не е автор на всички добавки в хранилището и не носи отговорност за съдържанието им.</disclaimer>
		<disclaimer lang="ca_ES">L&apos;equip de Kodi no ha fet tots els complements d&apos;aquest dipòsit i per tant no són responsables del seu contingut.</disclaimer>
		<disclaimer lang="cs_CZ">Tým Kodi nevytvořil všechny doplňky v tomto repozitáři a není zodpovědný za jejich obsah</disclaimer>
		<disclaimer lang="cy_GB">Nid Team Kodi wnaeth yr holl ychwanegion yn y storfa hon ac nid ydynt yn gyfrifol am eu cynnwys.</disclaimer>
		<disclaimer lang="da_DK">Team Kodi har ikke lavet alle add-ons i dette fjernlager og er ikke ansvarlig for deres indhold</disclaimer>
		<disclaimer lang="de_DE">Team Kodi hat nicht alle Addons dieses Repositorys selbst entwickelt und ist nicht für deren Inhalt verantwortlich</disclaimer>
		<disclaimer lang="el_GR">Η Ομάδα Kodi δεν δημιούργησε όλα τα πρόσθετα σε αυτό το αποθετήριο συνεπώς δεν είναι υπεύθυνη για το περιεχόμενό τους</disclaimer>
		<disclaimer lang="en_AU">Team Kodi did not make all the add-ons on this repository and are not responsible for their content</disclaimer>
		<disclaimer lang="en_GB">Team Kodi did not make all the add-ons on this repository and are not responsible for their content</disclaimer>
		<disclaimer lang="en_NZ">Team Kodi did not make all the add-ons on this repository and are not responsible for their content</disclaimer>
		<disclaimer lang="en_US">Team Kodi did not make all the add-ons on this repository and are not responsible for their content</disclaimer>
		<disclaimer lang="es_AR">No todos los add-ons en este repositorio han sido creados por el equipo de Kodi y este no es responsable de su contenido</disclaimer>
		<disclaimer lang="es_ES">El Equipo Kodi no ha creado todos los Add-ons de este repositorio y no es responsable de su contenido</disclaimer>
		<disclaimer lang="es_MX">El equipo de Kodi no hizo todos los complementos en este repositorio y no es responsable de su contenido</disclaimer>
		<disclaimer lang="et_EE">Kodi meeskond ei teinud kõiki lisasid selles hoidlas ja ei vastuta ka nende sisu eest</disclaimer>
		<disclaimer lang="eu_ES">Kodi taldeak ez ditu biltegi honetako gehigarri guztiak sortu eta ez da beren edukien erantzule.</disclaimer>
		<disclaimer lang="fa_IR">همه افزونه های این منبع محصول کار تیم کودی نیستند و این تیم مسئولیتی در قبال محتوای آنها ندارد.</disclaimer>
		<disclaimer lang="fi_FI">Team Kodi ei ole kehittänyt kaikkia varaston lisäosia, eikä ole vastuussa niiden sisällöstä.</disclaimer>
		<disclaimer lang="fr_CA">L’équipe Kodi n’a pas créé tous les addiciels de ce dépôt et n’est pas responsable de leur contenu</disclaimer>
		<disclaimer lang="fr_FR">L&apos;équipe Kodi n&apos;a pas créé tous les add-ons de ce magasin et n&apos;est pas responsable de leur contenu</disclaimer>
		<disclaimer lang="gl_ES">O equipo de Kodi non creou todos os Engadidos deste repositorio e non é responsábel do seu contido</disclaimer>
		<disclaimer lang="he_IL">צוות הפיתוח של Kodi לא יצר את כל ההרחבות שבמאגר זה ואיננו אחראי על תוכנן</disclaimer>
		<disclaimer lang="hr_HR">Kodi tim nije autor svih dodataka u ovom repozitoriju te kao takvi ne odgovaraju za njihov sadržaj</disclaimer>
		<disclaimer lang="hu_HU">Nem minden itt található kiegészítőt az Kodi csapat készített és nem vállal felelősséget azok tartalmáért</disclaimer>
		<disclaimer lang="id_ID">Tim Kodi tidak membuat semua pengaya pada repository ini dan tidak bertanggung jawab atas isinya.</disclaimer>
		<disclaimer lang="is_IS">Kodi-teymið framleiðir ekki allar þessar viðbætur og er ekki ábyrgt fyrir innihaldi þeirra.</disclaimer>
		<disclaimer lang="it_IT">Il team Kodi non ha creato tutti gli add-on su questo repository e non è responsabile del loro contenuto</disclaimer>
		<disclaimer lang="ja_JP">Kodi チームが、このリポジトリ上の全アドオンを作ったわけではありません。また、その内容についても責任は負いかねます。</disclaimer>
		<disclaimer lang="ko_KR">Kodi팀은 이 저장소의 모든 애드온을 만들지 않았으며 내용에 대해 책임지지 않습니다</disclaimer>
		<disclaimer lang="lt_LT">Kodi komanda netestavo priedų šioje saugykloje ir neatsako arba nėra atsakinga už jų turinį</disclaimer>
		<disclaimer lang="lv_LV">Kodi komanda nav izveidojusi visus šīs krātuves pielikumus un nav atbildīga par to saturu</disclaimer>
		<disclaimer lang="mk_MK">Kodi тимот ги нема направено сите овие додатоци и не е одговорен за нивната содржина</disclaimer>
		<disclaimer lang="ms_MY">Team Kodi tidak menghasilkan semua tambahan di dalam repositori ini dan tidak bertanggungjawab keatas kandungannya</disclaimer>
		<disclaimer lang="mt_MT">Team Kodi m&apos;għamilx l-add-ons kollha li hawn f&apos;dan ir-repożitorju u mhumiex responsabbli għall-kontenut tagħhom</disclaimer>
		<disclaimer lang="nb_NO">Team Kodi har ikke utviklet alle utvidelsene i denne pakkebrønnen og er ikke ansvarlig for deres innhold</disclaimer>
		<disclaimer lang="nl_NL">Team Kodi heeft niet alle add-ons in deze depot geschreven en is niet verantwoordelijk voor hun inhoud.</disclaimer>
		<disclaimer lang="pl_PL">Zespół Kodi nie stworzył wszystkich dodatków w tym repozytorium i nie ponosi odpowiedzialności za ich zawartość</disclaimer>
		<disclaimer lang="pt_BR">O Time do Kodi não produziu todos os add-ons deste repositório, e portanto não é responsável por seu conteúdo</disclaimer>
		<disclaimer lang="pt_PT">A Team Kodi não desenvolveu todos os add-ons neste repositório, e não é responsável pelo seu conteúdo.</disclaimer>
		<disclaimer lang="ro_RO">Echipa Kodi nu a creat toate aceste suplimente din acest depozit și nu este responsabilă pentru conținutul lor.</disclaimer>
		<disclaimer lang="ru_RU">Team Kodi не является разработчиком дополнений в этом репозитории и не несёт ответственности за их содержание</disclaimer>
		<disclaimer lang="sk_SK">Tým Kodi nevytvoril všetky doplnky v tomto repozitári a nie je zodpovedný za ich obsah</disclaimer>
		<disclaimer lang="sl_SI">Ekipa Kodi ni naredila vseh dodatkov v tem skladišču in ne odgovarja za njihovo vsebino</disclaimer>
		<disclaimer lang="sr_RS">Тим Kodi није направио све додатке у овом спремишту и није одговоран за њихов садржај</disclaimer>
		<disclaimer lang="sr_RS@latin">Tim-Kodi nije napravio sve dodatne programe u ovom spremištu i nije odgovoran za njihov sadržaj</disclaimer>
		<disclaimer lang="sv_SE">Team Kodi har inte gjort alla tillägg i förrådet och är inte ansvariga för innehållet i dessa</disclaimer>
		<disclaimer lang="szl">Ekipa Kodi niy rychtuje wszyjskich przidŏwkōw i niy ôdpadŏ za jejich zawartość</disclaimer>
		<disclaimer lang="tg_TJ">Гурӯҳи кории Kodi дар ин анбори нармафзор соҳиби ҳамаи барномаҳои иловагӣ намебошад ва барои мӯҳтавояшон ҷавобгар намебшад</disclaimer>
		<disclaimer lang="th_TH">ทีม Kodi ไม่ได้จัดทำ ส่วนเสริม ทั้งหมดในแหล่งข้อมูลโปรแกรมนี้ และจะไม่รับผิดชอบต่อเนื้อหาเหล่านั้น</disclaimer>
		<disclaimer lang="tr_TR">Kodi takımı bu depodaki eklentilerin birçoğunu kendisi geliştirmemiştir ve bunların içeriklerinden sorumlu değildir</disclaimer>
		<disclaimer lang="uk_UA">Зауважте, що не всі додатки в цьому Репозиторії створені Командою Kodi, і тому Команда не несе відповідальності за їх вміст.</disclaimer>
		<disclaimer lang="vi_VN">Đội ngũ Kodi không làm ra tất cả các add-on có trên kho chứa này và sẽ không chịu trách nhiệm về nội dung của các add-on đấy</disclaimer>
		<disclaimer lang="zh_CN">此插件库中插件并不完全由 Kodi 团队制作，对相关内容不承担责任</disclaimer>
		<disclaimer lang="zh_TW">這個附加元件庫的附加元件並非全部由 Kodi 團隊製作的，所以我們不對這些內容負責。</disclaimer>
	</extension>
</addon>

<addon id="script.advancedsettings.generator" name="Advanced Settings Generator" version="1.2.1" provider-name="jkmh">
	<requires>
		<import addon="xbmc.python" version="3.0.0"/>
		<import addon="xbmc.addon" version="14.0.0"/>
	</requires>
	<extension point="xbmc.python.script" library="default.py" />
	<extension point="xbmc.addon.metadata">
		<summary lang="cs_CZ">Výpočet a uložení souboru advancedsettings.xml</summary>
		<description lang="cs_CZ">Addon automaticky zjistí volnou paměť RAM. Podle doporučeného vzorce vypočítá a nakonfiguruje velikost cache v souboru advancedsettings.xml.[CR][CR]Bližší informace na https://repo.richardpodzemsky.cz/cache a https://kodi.wiki/view/Advancedsettings.xml</description>
		<platform>all</platform>
		<license>GPL 2.0</license>
		<assets>
			<icon>icon.png</icon>
		</assets>
	</extension>
</addon>

<addon id="script.calendar" name="Kalendář" version="1.0.0" provider-name="jkmh">
  <requires>
    <import addon="xbmc.python" version="3.0.0"/>
	<import addon="script.module.requests" version="2.22.0+matrix.1"/>
  </requires>
  <extension point="xbmc.python.script" library="main.py"/>
  <extension point="xbmc.service" library="service.py"/>
  <extension point="xbmc.addon.metadata">
    <summary lang="cs_CZ">Kalendář cz svátků a narozenin</summary>
    <description lang="cs_CZ">Připomíná svátky a narozeniny v rodině. Script je určen pro skin Confluence SCC. Pro ostatní skiny je nutný zásah do skinu.</description>
    <license>GPL 2.0</license>
    <platform>all</platform>
    <assets>
      <icon>icon.png</icon>
    </assets>
  </extension>
</addon>

<addon id="script.context.downloader" name="Video Downloader" version="1.0.3" provider-name="Sároš, jkmh">
    <requires>
        <import addon="xbmc.python" version="3.0.0" />
    </requires>
    <extension point="kodi.context.item">
        <menu id="kodi.core.main">
            <item library="addon.py">
                <label>[COLOR lightskyblue]Download video[/COLOR]</label>
                <visible>String.IsEqual(ListItem.dbtype,episode)|String.IsEqual(ListItem.dbtype,movie)|Container.Content(movies)|Container.Content(episodes)|Pvr.HasTVChannels</visible>
            </item>
        </menu>
    </extension>
    <extension point="xbmc.addon.metadata">
        <summary lang="en">Download Video from Plugins</summary>
        <platform>all</platform>
        <assets>
            <icon>icon.png</icon>
        </assets>
    </extension>
</addon>

<addon id="script.contextmenu" version="0.1.20" name="Context Menu" provider-name="JiRo">
    <requires>
        <import addon="xbmc.python" version="3.0.1" />
    </requires>
	<extension point="xbmc.service" library="service.py" />
    <extension point="xbmc.python.module" library="resources/lib/" />
	<extension point = "kodi.context.item" >
		<menu id = "kodi.core.main" >
			<item library="command.py" args="@item1_command,6" >
				<label>$INFO[Window(Home).Property(contextmenu_item1_name)]</label>
				<visible>Addon.SettingBool(script.contextmenu,item1_enable) + Integer.IsEqual(Addon.SettingInt(script.contextmenu,item1_position),6)</visible>
			</item>
			<item library="command.py" args="@item2_command,6" >
				<label>$INFO[Window(Home).Property(contextmenu_item2_name)]</label>
				<visible>Addon.SettingBool(script.contextmenu,item2_enable) + Integer.IsEqual(Addon.SettingInt(script.contextmenu,item2_position),6)</visible>
			</item>
			<item library="command.py" args="@item3_command,6" >
				<label>$INFO[Window(Home).Property(contextmenu_item3_name)]</label>
				<visible>Addon.SettingBool(script.contextmenu,item3_enable) + Integer.IsEqual(Addon.SettingInt(script.contextmenu,item3_position),6)</visible>
			</item>
			<item library="command.py" args="@item4_command,6" >
				<label>$INFO[Window(Home).Property(contextmenu_item4_name)]</label>
				<visible>Addon.SettingBool(script.contextmenu,item4_enable) + Integer.IsEqual(Addon.SettingInt(script.contextmenu,item4_position),6)</visible>
			</item>
			<!-- <item library="resourcestool.py" args="plugin.video.stream-cinema-2-release,auto_select_stream,true" > -->
				<!-- <label>30101</label> -->
				<!-- <visible>!Addon.SettingBool(plugin.video.stream-cinema-2-release,auto_select_stream) + System.AddonIsEnabled(plugin.video.stream-cinema-2-release) + [String.IsEqual(Container.PluginName,plugin.video.stream-cinema-2-release) | String.StartsWith(ListItem.Path,plugin://plugin.video.stream-cinema-2-release) | String.StartsWith(ListItem.Path,Addon.SettingStr(plugin.video.stream-cinema-2-release,movie_library_folder)) | String.StartsWith(ListItem.Path,Addon.SettingStr(plugin.video.stream-cinema-2-release,tvshow_library_folder))] + Addon.SettingBool(script.contextmenu,enable_select_stream)</visible> -->
			<!-- </item> -->
			<!-- <item library="tool.py" args="plugin.video.stream-cinema-2-release,auto_select_stream,false" > -->
				<!-- <label>30102</label> -->
				<!-- <visible>Addon.SettingBool(plugin.video.stream-cinema-2-release,auto_select_stream) + System.AddonIsEnabled(plugin.video.stream-cinema-2-release) + [String.IsEqual(Container.PluginName,plugin.video.stream-cinema-2-release) | String.StartsWith(ListItem.Path,plugin://plugin.video.stream-cinema-2-release) | String.StartsWith(ListItem.Path,Addon.SettingStr(plugin.video.stream-cinema-2-release,movie_library_folder)) | String.StartsWith(ListItem.Path,Addon.SettingStr(plugin.video.stream-cinema-2-release,tvshow_library_folder))] + Addon.SettingBool(script.contextmenu,enable_select_stream)</visible> -->
			<!-- </item> -->
			<!-- <item library="tool.py" args="plugin.video.stream-cinema-2-release,auto_select_stream.download,true" > -->
				<!-- <label>30111</label> -->
				<!-- <visible>!Addon.SettingBool(plugin.video.stream-cinema-2-release,auto_select_stream.download) + System.AddonIsEnabled(plugin.video.stream-cinema-2-release) + [String.IsEqual(Container.PluginName,plugin.video.stream-cinema-2-release) | String.StartsWith(ListItem.Path,plugin://plugin.video.stream-cinema-2-release) | String.StartsWith(ListItem.Path,Addon.SettingStr(plugin.video.stream-cinema-2-release,movie_library_folder)) | String.StartsWith(ListItem.Path,Addon.SettingStr(plugin.video.stream-cinema-2-release,tvshow_library_folder))] + Addon.SettingBool(script.contextmenu,enable_select_stream.download)</visible> -->
			<!-- </item> -->
			<!-- <item library="tool.py" args="plugin.video.stream-cinema-2-release,auto_select_stream.download,false" > -->
				<!-- <label>30112</label> -->
				<!-- <visible>Addon.SettingBool(plugin.video.stream-cinema-2-release,auto_select_stream.download) + System.AddonIsEnabled(plugin.video.stream-cinema-2-release) + [String.IsEqual(Container.PluginName,plugin.video.stream-cinema-2-release) | String.StartsWith(ListItem.Path,plugin://plugin.video.stream-cinema-2-release) | String.StartsWith(ListItem.Path,Addon.SettingStr(plugin.video.stream-cinema-2-release,movie_library_folder)) | String.StartsWith(ListItem.Path,Addon.SettingStr(plugin.video.stream-cinema-2-release,tvshow_library_folder))] + Addon.SettingBool(script.contextmenu,enable_select_stream.download)</visible> -->
			<!-- </item> -->
			<item library="command.py" args="@item1_command,5" >
				<label>$INFO[Window(Home).Property(contextmenu_item1_name)]</label>
				<visible>Addon.SettingBool(script.contextmenu,item1_enable) + Integer.IsEqual(Addon.SettingInt(script.contextmenu,item1_position),5)</visible>
			</item>
			<item library="command.py" args="@item2_command,5" >
				<label>$INFO[Window(Home).Property(contextmenu_item2_name)]</label>
				<visible>Addon.SettingBool(script.contextmenu,item2_enable) + Integer.IsEqual(Addon.SettingInt(script.contextmenu,item2_position),5)</visible>
			</item>
			<item library="command.py" args="@item3_command,5" >
				<label>$INFO[Window(Home).Property(contextmenu_item3_name)]</label>
				<visible>Addon.SettingBool(script.contextmenu,item3_enable) + Integer.IsEqual(Addon.SettingInt(script.contextmenu,item3_position),5)</visible>
			</item>
			<item library="command.py" args="@item4_command,5" >
				<label>$INFO[Window(Home).Property(contextmenu_item4_name)]</label>
				<visible>Addon.SettingBool(script.contextmenu,item4_enable) + Integer.IsEqual(Addon.SettingInt(script.contextmenu,item4_position),5)</visible>
			</item>
			<item library="command.py" args="Addon.OpenSettings(script.backgroundmusic)" >
				<label>30010</label>
				<visible>Window.IsActive(10002) + Addon.SettingBool(script.contextmenu,enable_background_music)</visible>
			</item>
			<item library="trailer.py" >
				<label>30020</label>
				<visible>!String.IsEmpty(ListItem.Trailer) + !String.Contains(ListItem.Trailer,plugin://plugin.video.stream-cinema-2-release) + Addon.SettingBool(script.contextmenu,enable_play_trailer)</visible>
			</item>
			<item library="searchtrailer.py" >
				<label>30030</label>
				<visible>System.AddonIsEnabled(plugin.video.youtube) + Addon.SettingBool(script.contextmenu,enable_search_trailer)</visible>
			</item>
			<item library="command.py" args="@item1_command,4" >
				<label>$INFO[Window(Home).Property(contextmenu_item1_name)]</label>
				<visible>Addon.SettingBool(script.contextmenu,item1_enable) + Integer.IsEqual(Addon.SettingInt(script.contextmenu,item1_position),4)</visible>
			</item>
			<item library="command.py" args="@item2_command,4" >
				<label>$INFO[Window(Home).Property(contextmenu_item2_name)]</label>
				<visible>Addon.SettingBool(script.contextmenu,item2_enable) + Integer.IsEqual(Addon.SettingInt(script.contextmenu,item2_position),4)</visible>
			</item>
			<item library="command.py" args="@item3_command,4" >
				<label>$INFO[Window(Home).Property(contextmenu_item3_name)]</label>
				<visible>Addon.SettingBool(script.contextmenu,item3_enable) + Integer.IsEqual(Addon.SettingInt(script.contextmenu,item3_position),4)</visible>
			</item>
			<item library="command.py" args="@item4_command,4" >
				<label>$INFO[Window(Home).Property(contextmenu_item4_name)]</label>
				<visible>Addon.SettingBool(script.contextmenu,item4_enable) + Integer.IsEqual(Addon.SettingInt(script.contextmenu,item4_position),4)</visible>
			</item>
			<item library="search.py" >
				<label>30051</label>
				<visible>Addon.SettingBool(script.contextmenu,common_item_search) + Addon.SettingBool(script.contextmenu,enable_search)</visible>
			</item>
			<item library="search.py" args="tmdb" >
				<label>30075</label>
				<visible>System.AddonIsEnabled(plugin.video.themoviedb.helper) + Addon.SettingBool(script.contextmenu,enable_search_tmdb) + !Addon.SettingBool(script.contextmenu,common_item_search) + Addon.SettingBool(script.contextmenu,enable_search)</visible>
			</item>
			<item library="search.py" args="yawsp" >
				<label>30077</label>
				<visible>System.AddonIsEnabled(plugin.video.yawsp) + Addon.SettingBool(script.contextmenu,enable_search_yawsp) + !Addon.SettingBool(script.contextmenu,common_item_search) + Addon.SettingBool(script.contextmenu,enable_search)</visible>
			</item>
			<!-- <item library="search.py" args="scc" > -->
				<!-- <label>30058</label> -->
				<!-- <visible>System.AddonIsEnabled(plugin.video.stream-cinema-2-release) + Addon.SettingBool(script.contextmenu,enable_search_scc) + !Addon.SettingBool(script.contextmenu,common_item_search) + Addon.SettingBool(script.contextmenu,enable_search)</visible> -->
			<!-- </item> -->
			<!-- <item library="search.py" args="ws" > -->
				<!-- <label>30060</label> -->
				<!-- <visible>System.AddonIsEnabled(plugin.video.stream-cinema-2-release) + Addon.SettingBool(script.contextmenu,enable_search_ws) + !Addon.SettingBool(script.contextmenu,common_item_search) + Addon.SettingBool(script.contextmenu,enable_search)</visible> -->
			<!-- </item> -->
			<item library="search.py" args="sc" >
				<label>30062</label>
				<visible>System.AddonIsEnabled(plugin.video.stream-cinema) + Addon.SettingBool(script.contextmenu,enable_search_sc) + !Addon.SettingBool(script.contextmenu,common_item_search) + Addon.SettingBool(script.contextmenu,enable_search)</visible>
			</item>
			<item library="search.py" args="netflix" >
				<label>30071</label>
				<visible>System.AddonIsEnabled(plugin.video.netflix) + Addon.SettingBool(script.contextmenu,enable_search_netflix) + !Addon.SettingBool(script.contextmenu,common_item_search) + Addon.SettingBool(script.contextmenu,enable_search)</visible>
			</item>
			<item library="search.py" args="yt" >
				<label>30067</label>
				<visible>System.AddonIsEnabled(plugin.video.youtube) + Addon.SettingBool(script.contextmenu,enable_search_yt) + !Addon.SettingBool(script.contextmenu,common_item_search) + Addon.SettingBool(script.contextmenu,enable_search)</visible>
			</item>
			<item library="search.py" args="library" >
				<label>30069</label>
				<visible>false + System.AddonIsEnabled(script.globalsearch) + Addon.SettingBool(script.contextmenu,enable_search_library) + !Addon.SettingBool(script.contextmenu,common_item_search) + Addon.SettingBool(script.contextmenu,enable_search)</visible>
			</item>
			<item library="smartsearch.py" args="hellspy" >
				<label>[COLOR blue]Smart hledání TMDb - Hellspy[/COLOR]</label>
				<visible>Addon.SettingBool(script.contextmenu,enable_smartsearch) +
						 System.AddonIsEnabled(plugin.video.themoviedb.helper) +
						 System.AddonIsEnabled(plugin.video.hellspy) +
						 String.StartsWith(ListItem.Path,plugin://plugin.video.themoviedb.helper) +
						 !String.IsEmpty(ListItem.DBTYPE)
				</visible>
			</item>
			<item library="smartsearch.py" args="sktonline" >
				<label>[COLOR orange]Smart hledání TMDb - SKTOnline[/COLOR]</label>
				<visible>Addon.SettingBool(script.contextmenu,enable_smartsearch) +
						 System.AddonIsEnabled(plugin.video.themoviedb.helper) +
						 System.AddonIsEnabled(plugin.video.sktonline) +
						 String.StartsWith(ListItem.Path,plugin://plugin.video.themoviedb.helper) +
						 !String.IsEmpty(ListItem.DBTYPE)
				</visible>
			</item>
			<item library="smartsearch.py" args="default" >
				<label>[COLOR green]Smart hledání TMDb - Webshare[/COLOR]</label>
				<visible>Addon.SettingBool(script.contextmenu,enable_smartsearch) +
						System.AddonIsEnabled(plugin.video.themoviedb.helper) +
						System.AddonIsEnabled(plugin.video.yawsp) +
						String.StartsWith(ListItem.Path,plugin://plugin.video.themoviedb.helper) +
						!String.IsEmpty(ListItem.DBTYPE)
				</visible>
			</item>
			<item library="command.py" args="@item1_command,3" >
				<label>$INFO[Window(Home).Property(contextmenu_item1_name)]</label>
				<visible>Addon.SettingBool(script.contextmenu,item1_enable) + Integer.IsEqual(Addon.SettingInt(script.contextmenu,item1_position),3)</visible>
			</item>
			<item library="command.py" args="@item2_command,3" >
				<label>$INFO[Window(Home).Property(contextmenu_item2_name)]</label>
				<visible>Addon.SettingBool(script.contextmenu,item2_enable) + Integer.IsEqual(Addon.SettingInt(script.contextmenu,item2_position),3)</visible>
			</item>
			<item library="command.py" args="@item3_command,3" >
				<label>$INFO[Window(Home).Property(contextmenu_item3_name)]</label>
				<visible>Addon.SettingBool(script.contextmenu,item3_enable) + Integer.IsEqual(Addon.SettingInt(script.contextmenu,item3_position),3)</visible>
			</item>
			<item library="command.py" args="@item4_command,3" >
				<label>$INFO[Window(Home).Property(contextmenu_item4_name)]</label>
				<visible>Addon.SettingBool(script.contextmenu,item4_enable) + Integer.IsEqual(Addon.SettingInt(script.contextmenu,item4_position),3)</visible>
			</item>
			<item library="command.py" args="Container.Refresh()" >
				<label>30190</label>
				<visible>!String.IsEmpty(Container.FolderPath) + Addon.SettingBool(script.contextmenu,enable_content_refresh)</visible>
			</item>
			<item library="command.py" args="Action(Delete)" >
				<label>30195</label>
				<visible>Addon.SettingBool(script.contextmenu,enable_delete)</visible>
			</item>
			<item library="command.py" args="@item1_command,2" >
				<label>$INFO[Window(Home).Property(contextmenu_item1_name)]</label>
				<visible>Addon.SettingBool(script.contextmenu,item1_enable) + Integer.IsEqual(Addon.SettingInt(script.contextmenu,item1_position),2)</visible>
			</item>
			<item library="command.py" args="@item2_command,2" >
				<label>$INFO[Window(Home).Property(contextmenu_item2_name)]</label>
				<visible>Addon.SettingBool(script.contextmenu,item2_enable) + Integer.IsEqual(Addon.SettingInt(script.contextmenu,item2_position),2)</visible>
			</item>
			<item library="command.py" args="@item3_command,2" >
				<label>$INFO[Window(Home).Property(contextmenu_item3_name)]</label>
				<visible>Addon.SettingBool(script.contextmenu,item3_enable) + Integer.IsEqual(Addon.SettingInt(script.contextmenu,item3_position),2)</visible>
			</item>
			<item library="command.py" args="@item4_command,2" >
				<label>$INFO[Window(Home).Property(contextmenu_item4_name)]</label>
				<visible>Addon.SettingBool(script.contextmenu,item4_enable) + Integer.IsEqual(Addon.SettingInt(script.contextmenu,item4_position),2)</visible>
			</item>
			<!-- <item library="restart.py" > -->
				<!-- <label>30196</label> -->
				<!-- <visible>Addon.SettingBool(script.contextmenu,enable_addon_restart)</visible> -->
			<!-- </item> -->
			<item library="setting.py" >
				<label>30191</label>
				<visible>!String.IsEmpty(Container.PluginName) + Addon.SettingBool(script.contextmenu,enable_addon_setting)</visible>
			</item>
			<item library="settingwidget.py" >
				<label>30191</label>
				<visible>String.IsEmpty(Container.PluginName) + !String.IsEmpty(ListItem.Path) + !String.IsEqual(ListItem.Path,plugin://) + !String.StartsWith(ListItem.Path,plugin://plugin.video.stream-cinema-2-release) + String.StartsWith(ListItem.Path,plugin://) + Addon.SettingBool(script.contextmenu,enable_addon_setting)</visible>
			</item>
			<!-- <item library="settingscc.py" > -->
				<!-- <label>30191</label> -->
				<!-- <visible>String.IsEmpty(Container.PluginName) + [String.StartsWith(ListItem.Path,plugin://plugin.video.stream-cinema-2-release) | String.StartsWith(ListItem.Path,Addon.SettingStr(plugin.video.stream-cinema-2-release,movie_library_folder)) | String.StartsWith(ListItem.Path,Addon.SettingStr(plugin.video.stream-cinema-2-release,tvshow_library_folder))] + Addon.SettingBool(script.contextmenu,enable_addon_setting)</visible> -->
			<!-- </item> -->
			<item library="command.py" args="ActivateWindow(settings)" >
				<label>30194</label>
				<visible>Addon.SettingBool(script.contextmenu,enable_setting)</visible>
			</item>
			<item library="command.py" args="Addon.OpenSettings(script.contextmenu)" >
				<label>30192</label>
				<visible>Addon.SettingBool(script.contextmenu,enable_self_setting)</visible>
			</item>
			<item library="iteminfo.py" >
				<label>30040</label>
				<visible>!String.IsEmpty(Container.Content) + Addon.SettingBool(script.contextmenu,enable_iteminfo)</visible>
			</item>
			<item library=".restart.py" >
				<label>[COLOR red]Restart pvr.hts[/COLOR]</label>
				<visible>Skin.HasSetting(easy_master)</visible>
			</item>
			<item library=".dump.py" >
				<label>[COLOR blue]Item Dump[/COLOR]</label>
				<visible>true</visible>
			</item>
			<item library="command.py" args="@item1_command,1" >
				<label>$INFO[Window(Home).Property(contextmenu_item1_name)]</label>
				<visible>Addon.SettingBool(script.contextmenu,item1_enable) + Integer.IsEqual(Addon.SettingInt(script.contextmenu,item1_position),1)</visible>
			</item>
			<item library="command.py" args="@item2_command,1" >
				<label>$INFO[Window(Home).Property(contextmenu_item2_name)]</label>
				<visible>Addon.SettingBool(script.contextmenu,item2_enable) + Integer.IsEqual(Addon.SettingInt(script.contextmenu,item2_position),1)</visible>
			</item>
			<item library="command.py" args="@item3_command,1" >
				<label>$INFO[Window(Home).Property(contextmenu_item3_name)]</label>
				<visible>Addon.SettingBool(script.contextmenu,item3_enable) + Integer.IsEqual(Addon.SettingInt(script.contextmenu,item3_position),1)</visible>
			</item>
			<item library="command.py" args="@item4_command,1" >
				<label>$INFO[Window(Home).Property(contextmenu_item4_name)]</label>
				<visible>Addon.SettingBool(script.contextmenu,item4_enable) + Integer.IsEqual(Addon.SettingInt(script.contextmenu,item4_position),1)</visible>
			</item>
		</menu>
	</extension>
	<extension point="xbmc.addon.metadata">
        <summary lang="cs_cz">Context Menu - Easy Tools kategorie</summary>
        <description lang="cs_cz">Přidává různé a užitečné položky do kontextového menu. Umožňuje také uživatelům si s jeho pomocí definovat vlastní položky tohoto menu.[CR][CR]Další informace najdete na www.xbmc-kodi.cz/prispevek-context-menu.</description>
        <disclaimer  lang="cs_cz">Experimentální verze...</disclaimer>
        <summary lang="en_gb">Context Menu - Easy Tools category</summary>
        <description lang="en_gb">Adds various and useful items to the context menu. Addon also offers users to define their own menu items.[CR][CR]You can find more information at www.xbmc-kodi.cz/prispevek-context-menu (czech only).</description>
        <disclaimer  lang="en_gb">Experimental version...</disclaimer>
        <summary lang="sk_sk">Context Menu - Easy Tools kategórie</summary>
        <description lang="sk_sk">Pridáva rôzne a užitočné položky do kontextového menu. Umožňuje taktiež užívateľom si s jeho pomocou definovať vlastné položky tohto menu.[CR][CR]Ďalšie informácie nájdete na www.xbmc-kodi.cz/prispevek-context-menu.</description>
        <disclaimer  lang="sk_sk">Experimentálna verzia...</disclaimer>
        <language>cs_cz</language>
		<platform>all</platform>
        <license>GPL 2.0</license>
		<forum>https://www.xbmc-kodi.cz/prispevek-context-menu</forum>
		<website></website>
		<email></email>
		<source></source>
		<news>v0.1.20 (2025-05-01)
- minor changes in addon.xml
		</news>
		<assets>
			<icon>resources/icon.png</icon>
            <screenshot>resources/screenshot01.jpg</screenshot>
            <screenshot>resources/screenshot02.jpg</screenshot>
            <screenshot>resources/screenshot03.jpg</screenshot>
            <screenshot>resources/screenshot04.jpg</screenshot>
            <screenshot>resources/screenshot05.jpg</screenshot>
		</assets>
	</extension>
</addon>

<addon id="script.copernicus.sentinel" name="Copernicus Sentinel" version="1.1.0" provider-name="jkmh">
  <requires>
    <import addon="xbmc.python" version="3.0.0"/>
	<import addon="script.module.oauthlib" version="3.2.2"/>
	<import addon="script.module.requests_oauthlib" version="1.3.1+matrix.1"/>
	<!-- <import addon="script.module.requests" version="2.21.0" /> -->
  </requires>
  <extension point="xbmc.python.script" library="main.py">
    <provides>script</provides>
  </extension>
  <extension point="xbmc.addon.metadata">
    <summary lang="cs_CZ">Stahování družicových snímků</summary>
    <description lang="en_GB"></description>
    <description lang="cs_CZ">Stahujeme družicové snímky Sentinel-2 z programu Copernicus.[CR]Vyzkoušíme generování/stahování čerstvých snímků z družic mise Sentinel-2.[CR][Článek na Živě.cz][CR](https://www.zive.cz/clanky/programujeme-v-pythonu-jak-uplne-zadarmo-stahnout-cerstve-druzicove-snimky-libovolneho-mista-v-cesku/sc-3-a-229892/default.aspx)**</description>
    <license>GPL-3.0-only</license>
    <platform>all</platform>
    <assets>
      <icon>icon.png</icon>
    </assets>
  </extension>
</addon>

<addon id="script.iperf3.tool" name="iPerf3 Bandwidth Tool" version="1.0.0" provider-name="jkmh">
    <requires>
        <import addon="xbmc.python" version="3.0.0" />
    </requires>
    <extension point="xbmc.python.script" library="default.py">
        <provides>executable</provides>
    </extension>
    <extension point="xbmc.addon.metadata">
        <summary>Měření rychlosti pomocí iPerf3</summary>
        <description>Addon pro spuštění iPerf3. Funkční jen v prostředí Android a Linux.</description>
        <platform>android linux</platform>
		<assets>
            <icon>icon.png</icon>
        </assets>
    </extension>
</addon>

<addon id="script.kitchen.timer" name="Minutka" version="0.0.1" provider-name="jkmh">
	<requires>
		<import addon="xbmc.python" version="3.0.0"/>
	</requires>
	<extension point="xbmc.python.script" library="timer.py">
		<provides>executable</provides>
	</extension>
	<extension point="xbmc.addon.metadata">
		<platform>linux</platform>
		<summary lang="en">Kuchyňská minutka</summary>
		<description lang="en">Kuchyňská minutka</description>
		<license>GNU General Public License, v2</license>
		<language>cz</language>
		<assets>
			<icon>kitchen.png</icon>
		</assets>
	</extension>
</addon>

<addon id="script.skip.ads" name="Skip Ads" version="1.0.1" provider-name="jkmh">
  <requires>
    <import addon="xbmc.python" version="3.0.0"/>
	<import addon="xbmc.addon" version="14.0.0"/>
  </requires>
  <extension point="xbmc.python.script" library="main.py"/>
  <extension point="xbmc.addon.metadata">
    <summary lang="en_GB"></summary>
    <description lang="en_GB"></description>
    <description lang="cs_CZ">Přeskočení reklamy v TV vysílání</description>
    <license>GPL-3.0-only</license>
    <platform>all</platform>
    <assets>
      <icon>icon.png</icon>
    </assets>
  </extension>
</addon>

<addon id="script.sledovanitv" version="1.1.1" name="Script SledovaniTV" provider-name="jkmh">
    <requires>
        <import addon="xbmc.python" version="3.0.0" />
        <import addon="script.module.requests" />
    </requires>
	<extension point="xbmc.python.script" library="main.py"/>
	<extension point="xbmc.service" library="service.py"/>
    <extension point="xbmc.addon.metadata">
        <summary lang="cs">Script SledovaniTV</summary>
        <summary lang="en">Script SledovaniTV</summary>
        <description lang="cs">Script pro stažení a tvorbu playlistu a EPG pro IPTV Simple Client</description>
        <assets>
            <icon>icon.png</icon>
        </assets>
    </extension>
</addon>

<addon id="script.sms.epg.generator" name="SMS EPG Generator" version="1.1.1" provider-name="jkmh">
	<requires>
        <import addon="xbmc.python" version="3.0.0" />
        <import addon="script.module.requests" />
    </requires>
	<extension point="xbmc.python.script" library="main.py"/>
    <extension point="xbmc.service" library="service.py"/>
	<extension point="xbmc.addon.metadata">
		<summary lang="en_GB"></summary>
		<description lang="en_GB"></description>
		<description lang="cs_CZ">Generuje EPG ze serveru SMS.CZ</description>
		<license>GPL-3.0-only</license>
		<platform>all</platform>
		<assets>
		  <icon>icon.png</icon>
		</assets>
	</extension>
</addon>

<addon id="script.speedmeter" name="Speed Meter" version="1.0.2" provider-name="JiRo">
	<requires>
		<import addon="xbmc.python" version="3.0.0"/>
		<import addon="script.module.requests" version="2.22.0"/>
	</requires>
	<extension point="xbmc.python.script" library="script.py">
		<provides>executable</provides>
	</extension>
	<extension  point="xbmc.service" library="service.py" />
    <extension point="xbmc.python.module" library="resources/lib/"/>
	<extension point="xbmc.addon.metadata">
		<summary lang="cs_CZ">Doplněk pro on-line měření rychlosti komunikace na síťovém rozhraní systému, na kterém běží Kodi.</summary>
		<description lang="cs_CZ">Aplikace je momentálně v Alpha verzi a do konečné podoby je ještě dlouhá cesta.
Tato verze je tedy určena pro nedočkavé zájemce o tento doplněk a je třeba ji chápat jako experimentální.
Je určena pouze pro LibreELEC a CoreELEC verze 20 a vyšší a pravděpodobně i pro systémy Linux (neověřeno).
V současné chvíli umí doplněk monitorovat pouze komunikaci na rozhraní eth0. Využívá pro to systémové aplikace ifconfig, grep a sed.

Explicitně podporované skiny: [B]Estuary, Estuary Easy[/B]
Ověřené skiny (default):[B]Confluence, Confluence SCC Omega, Estuary (Hardo) SCC Omega[/B]
		</description>
        <disclaimer  lang="cs_CZ">Tato verze je experimentální.[CR]Její použití v produktivních prostředích Kodi jen na vlastní nebezpečí.</disclaimer>
        <language>cs</language>
		<platform>linux</platform>
        <license>GPL 2.0</license>
		<forum>https://www.xbmc-kodi.cz/prispevek-speed-meter</forum>
		<website></website>
		<email></email>
		<source></source>
		<assets>
			<icon>resources/icon.png</icon>
            <screenshot>resources/screenshot01.jpg</screenshot>
            <screenshot>resources/screenshot02.jpg</screenshot>
            <screenshot>resources/screenshot03.jpg</screenshot>
            <screenshot>resources/screenshot04.jpg</screenshot>
            <screenshot>resources/screenshot05.jpg</screenshot>
		</assets>
		<news>v1.0.1 2024-12-11
- journal functions deleted
		</news>
	</extension>
</addon>

<addon id="script.tools.box" name="Kodi Tools Box" version="1.1.8" provider-name="jkmh">
	<requires>
		<import addon="xbmc.python" version="3.0.0"/>
	</requires>
	<extension point="xbmc.python.script" library="default.py">
		<provides>executable</provides>
	</extension>
	<extension point="xbmc.addon.metadata">
		<summary lang="cs_CZ">Zjednodušení práce v Kodi</summary>
		<description lang="cs_CZ">Sbírka různých nástrojů , které se mohou hodit.[CR][CR] - Advanced settings - nastavení videocache jedním kliknutím[CR] - Záloha/Obnovení nastavení SCC (settings.xml) jedním kliknutím[CR] - Čistící nástroje</description>
		<platform>android linux windows</platform>
        <license>GPL-2.0-or-later</license>
		<assets>
			<icon>icon.png</icon>
		</assets>
	</extension>
</addon>

<addon id="script.ws.download.bandwith" version="1.0.0" name="Webshare Download Bandwith" provider-name="jkmh">
    <requires>
        <import addon="xbmc.python" version="3.0.0"/>
    </requires>
    <extension point="xbmc.python.script" library="main.py">
        <provides>executable</provides>
    </extension>
    <extension point="xbmc.addon.metadata">
        <summary lang="cz">edit</summary>
        <description lang="cz">Měření rychlosti stahování ze serverů Webshare.[CR]Script stahuje současně testovací soubor ze všech serverů</description>
        <platform>android linux</platform>
    </extension>
</addon>

<addon id="service.autoexec.journalctl" name="Autoexec Journalctl" version="1.0.0" provider-name="jkmh">
	<requires>
		<import addon="xbmc.python" version="3.0.0"/>
	</requires>
	<extension point="xbmc.service" library="default.py">
	</extension>
	<extension point="xbmc.addon.metadata">
		<summary lang="en_GB">Automatically saves system logs (journalctl) to a file when Kodi starts.</summary>
		<description lang="en_GB">Automatically saves system logs (journalctl) to a file when Kodi starts.</description>
		<platform>all</platform>
		<license>GNU GENERAL PUBLIC LICENSE Version 2</license>
	</extension>
</addon>

<addon id="service.netspeed.monitor" name="Netspeed Monitor" version="1.0.5" provider-name="jkmh">
  <requires>
    <import addon="xbmc.python" version="3.0.0"/>
	<import addon="xbmc.addon" version="14.0.0"/>
  </requires>
  <extension point="xbmc.service" library="netspeed.py"/>
  <extension point="xbmc.addon.metadata">
    <summary lang="en_GB">Netspeed monitor for LAN/WIFI interface</summary>
    <description lang="en_GB">Netspeed monitor for LAN/WIFI interface</description>
    <description lang="cs_CZ">Addon k zobrazení datového toku rozhraním LAN/WIFI pro skin Confluence SCC. Po nainstalování se automaticky rozšíří možnosti nastavení. K zobrazení informací v jiných skinech je nutná jejich dodatečná editace.</description>
    <license>GPL-3.0-only</license>
    <platform>all</platform>
    <assets>
      <icon>icon.png</icon>
    </assets>
  </extension>
</addon>

<addon id="service.ping.monitor" name="Ping Monitor" version="1.1.9" provider-name="jkmh">
  <requires>
    <import addon="xbmc.python" version="3.0.0"/>
  </requires>
  <extension point="xbmc.service" library="ping.py"/>
  <extension point="xbmc.addon.metadata">
    <summary lang="cs_CZ">Monitoring dostupnosti sítě a internetu</summary>
    <description lang="cs_CZ">Kontinuální zjišťování dostupnosti internetu ikonami na hlavní obrazovce.[CR][CR]Doplněk pro skin Confluence SCC. Po instalaci se rozšíří možnosti v nastavení skinu. U ostatních skinů je nutná jejich dodatečná editace.</description>
    <license>GPL 2.0</license>
    <platform>all</platform>
    <assets>
      <icon>icon.png</icon>
    </assets>
  </extension>
</addon>

<addon id="service.stv.web.server" name="IPTV STV Server" version="1.0.0" provider-name="Sároš">
    <requires>
        <import addon="xbmc.python" version="3.0.0"/>
        <import addon="script.module.requests" />
        <import addon="script.module.pycryptodome" />
        <import addon="script.module.bottle" />
        <import addon="script.module.routing" />
    </requires>
    <extension point="xbmc.service" library="service.py">
    </extension>
    <extension point="xbmc.python.pluginsource" library="main.py">
    </extension>
    <extension point="xbmc.addon.metadata">
        <platform>all</platform>
        <summary lang="cs_CS">IPTV Web Server</summary>
        <description lang="cs_CS">Tento doplněk vám pomocí webového serveru zpřístupní cestu k vaším streamům v rámci lokální sítě.</description>
        <news>v1.0.0 (24.3.2023)
        </news>
        <assets>
			<icon>icon.png</icon>
        </assets>
    </extension>
</addon>

<addon id="service.temperature" name="Teploměr" version="1.0.0" provider-name="jkmh">
  <requires>
    <import addon="xbmc.python" version="3.0.0"/>
	<import addon="script.module.requests" version="2.22.0+matrix.1"/>
  </requires>
  <extension point="xbmc.service" library="main.py"/>
  <extension point="xbmc.addon.metadata">
    <summary lang="en_GB"></summary>
    <description lang="en_GB"></description>
    <description lang="cs_CZ">Vyčítání teplot z domácího teploměru</description>
    <license>GPL-3.0-only</license>
    <platform>all</platform>
    <assets>
      <icon>icon.png</icon>
    </assets>
  </extension>
</addon>
</addons>
